classdirectory/__init__.py
classdirectory/classdirectory.py
classdirectory-0.0.4.dist-info/DESCRIPTION.rst
classdirectory-0.0.4.dist-info/METADATA
classdirectory-0.0.4.dist-info/metadata.json
classdirectory-0.0.4.dist-info/RECORD
classdirectory-0.0.4.dist-info/top_level.txt
classdirectory-0.0.4.dist-info/WHEEL
