Metadata-Version: 2.0
Name: classdirectory
Version: 0.0.4
Summary: Find classmates in module.
Home-page: https://github.com/fly/classdirectory
Author: Jon Chen
Author-email: bsd@voltaire.sh
License: MIT
Platform: UNKNOWN
Classifier: Intended Audience :: Developers
Classifier: License :: OSI Approved :: Apache Software License
Classifier: Operating System :: POSIX :: Linux
Classifier: Programming Language :: Python
Classifier: Programming Language :: Python :: 3
Classifier: Programming Language :: Python :: 3.2
Classifier: Programming Language :: Python :: 3.3
Classifier: Programming Language :: Python :: 3.4
